{"id": "https://openalex.org/W4304161328", "doi": "https://doi.org/10.22394/2079-1690-2022-1-3-98-105", "title": "ANTI-CRISIS MANAGEMENT OF A MULTI-LAYERED ECONOMY UNDER SANCTIONS BASED ON THE CONCEPT OF DOMINANT FACTORS OF PRODUCTION", "display_name": "ANTI-CRISIS MANAGEMENT OF A MULTI-LAYERED ECONOMY UNDER SANCTIONS BASED ON THE CONCEPT OF DOMINANT FACTORS OF PRODUCTION", "publication_year": 2022, "publication_date": "2022-09-01", "ids": {"openalex": "https://openalex.org/W4304161328", "doi": "https://doi.org/10.22394/2079-1690-2022-1-3-98-105"}, "language": "en", "primary_location": {"is_oa": true, "landing_page_url": "https://doi.org/10.22394/2079-1690-2022-1-3-98-105", "pdf_url": null, "source": {"id": "https://openalex.org/S4210176877", "display_name": "STATE AND MUNICIPAL MANAGEMENT SCHOLAR NOTES", "issn_l": "2079-1690", "issn": ["2079-1690", "2687-0290"], "is_oa": true, "is_in_doaj": false, "is_indexed_in_scopus": false, "is_core": false, "host_organization": null, "host_organization_name": null, "host_organization_lineage": [], "host_organization_lineage_names": [], "type": "journal"}, "license": null, "license_id": null, "version": "publishedVersion", "is_accepted": true, "is_published": true}, "type": "article", "type_crossref": "journal-article", "indexed_in": ["crossref"], "open_access": {"is_oa": true, "oa_status": "gold", "oa_url": "https://doi.org/10.22394/2079-1690-2022-1-3-98-105", "any_repository_has_fulltext": false}, "authorships": [{"author_position": "first", "author": {"id": "https://openalex.org/A5066508854", "display_name": "\u0415\u0440\u0435\u043c\u0435\u043d\u043a\u043e \u041a\u043e\u043d\u0441\u0442\u0430\u043d\u0442\u0438\u043d \u041f\u0430\u0432\u043b\u043e\u0432\u0438\u0447", "orcid": null}, "institutions": [], "countries": [], "is_corresponding": false, "raw_author_name": "\u0415\u0440\u0435\u043c\u0435\u043d\u043a\u043e \u041a\u043e\u043d\u0441\u0442\u0430\u043d\u0442\u0438\u043d \u041f\u0430\u0432\u043b\u043e\u0432\u0438\u0447", "raw_affiliation_strings": ["\u041f\u0440\u0435\u0437\u0438\u0434\u0435\u043d\u0442\u0435 \u0420\u0424, \u0420\u043e\u0441\u0442\u043e\u0432-\u043d\u0430-\u0414\u043e\u043d\u0443, \u0420\u043e\u0441\u0441\u0438\u044f"], "affiliations": [{"raw_affiliation_string": "\u041f\u0440\u0435\u0437\u0438\u0434\u0435\u043d\u0442\u0435 \u0420\u0424, \u0420\u043e\u0441\u0442\u043e\u0432-\u043d\u0430-\u0414\u043e\u043d\u0443, \u0420\u043e\u0441\u0441\u0438\u044f", "institution_ids": []}]}, {"author_position": "middle", "author": {"id": "https://openalex.org/A5096290038", "display_name": "\u0415\u0444\u0440\u0435\u043c\u043e\u0432 \u0412\u0430\u0434\u0438\u043c \u0412\u0430\u0434\u0438\u043c\u043e\u0432\u0438\u0447", "orcid": null}, "institutions": [{"id": "https://openalex.org/I263417816", "display_name": "The Russian Presidential Academy of National Economy and Public Administration", "ror": "https://ror.org/04xnm9a92", "country_code": "RU", "type": "government", "lineage": ["https://openalex.org/I263417816"]}], "countries": ["RU"], "is_corresponding": false, "raw_author_name": "\u0415\u0444\u0440\u0435\u043c\u043e\u0432 \u0412\u0430\u0434\u0438\u043c \u0412\u0430\u0434\u0438\u043c\u043e\u0432\u0438\u0447", "raw_affiliation_strings": ["South-Russia Institute of Management -branch of Russian Presidential Academy of National Economy and Public Administration, Rostov-on-Don, Russia"], "affiliations": [{"raw_affiliation_string": "South-Russia Institute of Management -branch of Russian Presidential Academy of National Economy and Public Administration, Rostov-on-Don, Russia", "institution_ids": ["https://openalex.org/I263417816"]}]}, {"author_position": "last", "author": {"id": "https://openalex.org/A5079739038", "display_name": "\u0418\u0432\u0430\u043d\u043e\u0432 \u0412\u044f\u0447\u0435\u0441\u043b\u0430\u0432 \u0415\u0432\u0433\u0435\u043d\u044c\u0435\u0432\u0438\u0447", "orcid": null}, "institutions": [{"id": "https://openalex.org/I4210142928", "display_name": "Rostov Institute of Law of the Ministry of Internal Affairs of the Russian Federation", "ror": "https://ror.org/052j3fv27", "country_code": "RU", "type": "education", "lineage": ["https://openalex.org/I4210142928"]}, {"id": "https://openalex.org/I263417816", "display_name": "The Russian Presidential Academy of National Economy and Public Administration", "ror": "https://ror.org/04xnm9a92", "country_code": "RU", "type": "government", "lineage": ["https://openalex.org/I263417816"]}], "countries": ["RU"], "is_corresponding": false, "raw_author_name": "\u0418\u0432\u0430\u043d\u043e\u0432 \u0412\u044f\u0447\u0435\u0441\u043b\u0430\u0432 \u0415\u0432\u0433\u0435\u043d\u044c\u0435\u0432\u0438\u0447", "raw_affiliation_strings": ["South-Russia Institute of Management -branch of Russian Presidential Academy of National Economy and Public Administration, Rostov-on-Don, Russia", "Volgodonsk branch of Rostov Law Institute of Ministry of Internal Affairs of Russia, Volgodonsk, Russia", "\u0412\u043e\u043b\u0433\u043e\u0434\u043e\u043d\u0441\u043a\u0438\u0439 \u0444\u0438\u043b\u0438\u0430\u043b \u0420\u043e\u0441\u0442\u043e\u0432\u0441\u043a\u043e\u0433\u043e \u044e\u0440\u0438\u0434\u0438\u0447\u0435\u0441\u043a\u043e\u0433\u043e \u0438\u043d\u0441\u0442\u0438\u0442\u0443\u0442\u0430 \u041c\u0412\u0414 \u0420\u043e\u0441\u0441\u0438\u0438, \u0412\u043e\u043b\u0433\u043e\u0434\u043e\u043d\u0441\u043a, \u0420\u043e\u0441\u0441\u0438\u044f"], "affiliations": [{"raw_affiliation_string": "Volgodonsk branch of Rostov Law Institute of Ministry of Internal Affairs of Russia, Volgodonsk, Russia", "institution_ids": ["https://openalex.org/I4210142928"]}, {"raw_affiliation_string": "South-Russia Institute of Management -branch of Russian Presidential Academy of National Economy and Public Administration, Rostov-on-Don, Russia", "institution_ids": ["https://openalex.org/I263417816"]}, {"raw_affiliation_string": "\u0412\u043e\u043b\u0433\u043e\u0434\u043e\u043d\u0441\u043a\u0438\u0439 \u0444\u0438\u043b\u0438\u0430\u043b \u0420\u043e\u0441\u0442\u043e\u0432\u0441\u043a\u043e\u0433\u043e \u044e\u0440\u0438\u0434\u0438\u0447\u0435\u0441\u043a\u043e\u0433\u043e \u0438\u043d\u0441\u0442\u0438\u0442\u0443\u0442\u0430 \u041c\u0412\u0414 \u0420\u043e\u0441\u0441\u0438\u0438, \u0412\u043e\u043b\u0433\u043e\u0434\u043e\u043d\u0441\u043a, \u0420\u043e\u0441\u0441\u0438\u044f", "institution_ids": []}]}], "institution_assertions": [], "countries_distinct_count": 1, "institutions_distinct_count": 2, "corresponding_author_ids": [], "corresponding_institution_ids": [], "apc_list": null, "apc_paid": null, "fwci": 0.176, "has_fulltext": true, "fulltext_origin": "pdf", "cited_by_count": 1, "citation_normalized_percentile": {"value": 0.526516, "is_in_top_1_percent": false, "is_in_top_10_percent": false}, "cited_by_percentile_year": {"min": 59, "max": 69}, "biblio": {"volume": "1", "issue": "3", "first_page": "98", "last_page": "105"}, "is_retracted": false, "is_paratext": false, "primary_topic": {"id": "https://openalex.org/T13007", "display_name": "Economic Sanctions and International Relations", "score": 0.8723, "subfield": {"id": "https://openalex.org/subfields/2002", "display_name": "Economics and Econometrics"}, "field": {"id": "https://openalex.org/fields/20", "display_name": "Economics, Econometrics and Finance"}, "domain": {"id": "https://openalex.org/domains/2", "display_name": "Social Sciences"}}, "topics": [{"id": "https://openalex.org/T13007", "display_name": "Economic Sanctions and International Relations", "score": 0.8723, "subfield": {"id": "https://openalex.org/subfields/2002", "display_name": "Economics and Econometrics"}, "field": {"id": "https://openalex.org/fields/20", "display_name": "Economics, Econometrics and Finance"}, "domain": {"id": "https://openalex.org/domains/2", "display_name": "Social Sciences"}}, {"id": "https://openalex.org/T12667", "display_name": "Economic and Technological Developments in Russia", "score": 0.7987, "subfield": {"id": "https://openalex.org/subfields/3303", "display_name": "Development"}, "field": {"id": "https://openalex.org/fields/33", "display_name": "Social Sciences"}, "domain": {"id": "https://openalex.org/domains/2", "display_name": "Social Sciences"}}, {"id": "https://openalex.org/T13609", "display_name": "Economic, Social, and Public Health Issues in Russia and Globally", "score": 0.7662, "subfield": {"id": "https://openalex.org/subfields/1803", "display_name": "Management Science and Operations Research"}, "field": {"id": "https://openalex.org/fields/18", "display_name": "Decision Sciences"}, "domain": {"id": "https://openalex.org/domains/2", "display_name": "Social Sciences"}}], "keywords": [{"id": "https://openalex.org/keywords/investment", "display_name": "Investment", "score": 0.6615437}, {"id": "https://openalex.org/keywords/capital", "display_name": "Capital (architecture)", "score": 0.6303067}, {"id": "https://openalex.org/keywords/factors-of-production", "display_name": "Factors of production", "score": 0.52638364}, {"id": "https://openalex.org/keywords/means-of-production", "display_name": "Means of production", "score": 0.4817667}, {"id": "https://openalex.org/keywords/capital-investment", "display_name": "Capital investment", "score": 0.44932374}], "concepts": [{"id": "https://openalex.org/C2778348673", "wikidata": "https://www.wikidata.org/wiki/Q739302", "display_name": "Production (economics)", "level": 2, "score": 0.72522366}, {"id": "https://openalex.org/C2778069335", "wikidata": "https://www.wikidata.org/wiki/Q32098", "display_name": "Sanctions", "level": 2, "score": 0.7201698}, {"id": "https://openalex.org/C27548731", "wikidata": "https://www.wikidata.org/wiki/Q88272", "display_name": "Investment (military)", "level": 3, "score": 0.6615437}, {"id": "https://openalex.org/C83646750", "wikidata": "https://www.wikidata.org/wiki/Q193893", "display_name": "Capital (architecture)", "level": 2, "score": 0.6303067}, {"id": "https://openalex.org/C3019953208", "wikidata": "https://www.wikidata.org/wiki/Q159", "display_name": "Russian federation", "level": 2, "score": 0.53268033}, {"id": "https://openalex.org/C2781316041", "wikidata": "https://www.wikidata.org/wiki/Q1230584", "display_name": "Diversity (politics)", "level": 2, "score": 0.5289369}, {"id": "https://openalex.org/C16927522", "wikidata": "https://www.wikidata.org/wiki/Q210947", "display_name": "Factors of production", "level": 3, "score": 0.52638364}, {"id": "https://openalex.org/C59659247", "wikidata": "https://www.wikidata.org/wiki/Q11990", "display_name": "Reproduction", "level": 2, "score": 0.5142031}, {"id": "https://openalex.org/C136264566", "wikidata": "https://www.wikidata.org/wiki/Q159810", "display_name": "Economy", "level": 1, "score": 0.4916764}, {"id": "https://openalex.org/C188284582", "wikidata": "https://www.wikidata.org/wiki/Q260747", "display_name": "Means of production", "level": 4, "score": 0.4817667}, {"id": "https://openalex.org/C144133560", "wikidata": "https://www.wikidata.org/wiki/Q4830453", "display_name": "Business", "level": 0, "score": 0.47962508}, {"id": "https://openalex.org/C2985722716", "wikidata": "https://www.wikidata.org/wiki/Q4290", "display_name": "Capital investment", "level": 2, "score": 0.44932374}, {"id": "https://openalex.org/C74363100", "wikidata": "https://www.wikidata.org/wiki/Q273005", "display_name": "Economic system", "level": 1, "score": 0.44298193}, {"id": "https://openalex.org/C34447519", "wikidata": "https://www.wikidata.org/wiki/Q179522", "display_name": "Market economy", "level": 1, "score": 0.3625235}, {"id": "https://openalex.org/C26271046", "wikidata": "https://www.wikidata.org/wiki/Q187097", "display_name": "Economic geography", "level": 1, "score": 0.36236125}, {"id": "https://openalex.org/C162324750", "wikidata": "https://www.wikidata.org/wiki/Q8134", "display_name": "Economics", "level": 0, "score": 0.35314232}, {"id": "https://openalex.org/C17744445", "wikidata": "https://www.wikidata.org/wiki/Q36442", "display_name": "Political science", "level": 0, "score": 0.3262073}, {"id": "https://openalex.org/C205649164", "wikidata": "https://www.wikidata.org/wiki/Q1071", "display_name": "Geography", "level": 0, "score": 0.29468316}, {"id": "https://openalex.org/C2776943663", "wikidata": "https://www.wikidata.org/wiki/Q165687", "display_name": "Human capital", "level": 2, "score": 0.20959702}, {"id": "https://openalex.org/C105639569", "wikidata": "https://www.wikidata.org/wiki/Q582577", "display_name": "Economic policy", "level": 1, "score": 0.18814677}, {"id": "https://openalex.org/C44750222", "wikidata": "https://www.wikidata.org/wiki/Q1897397", "display_name": "Financial capital", "level": 3, "score": 0.16635838}, {"id": "https://openalex.org/C199539241", "wikidata": "https://www.wikidata.org/wiki/Q7748", "display_name": "Law", "level": 1, "score": 0.11470702}, {"id": "https://openalex.org/C175444787", "wikidata": "https://www.wikidata.org/wiki/Q39072", "display_name": "Microeconomics", "level": 1, "score": 0.08716074}, {"id": "https://openalex.org/C166957645", "wikidata": "https://www.wikidata.org/wiki/Q23498", "display_name": "Archaeology", "level": 1, "score": 0.07981366}, {"id": "https://openalex.org/C10138342", "wikidata": "https://www.wikidata.org/wiki/Q43015", "display_name": "Finance", "level": 1, "score": 0.0797987}, {"id": "https://openalex.org/C18903297", "wikidata": "https://www.wikidata.org/wiki/Q7150", "display_name": "Ecology", "level": 1, "score": 0.0}, {"id": "https://openalex.org/C94625758", "wikidata": "https://www.wikidata.org/wiki/Q7163", "display_name": "Politics", "level": 2, "score": 0.0}, {"id": "https://openalex.org/C86803240", "wikidata": "https://www.wikidata.org/wiki/Q420", "display_name": "Biology", "level": 0, "score": 0.0}], "mesh": [], "locations_count": 1, "locations": [{"is_oa": true, "landing_page_url": "https://doi.org/10.22394/2079-1690-2022-1-3-98-105", "pdf_url": null, "source": {"id": "https://openalex.org/S4210176877", "display_name": "STATE AND MUNICIPAL MANAGEMENT SCHOLAR NOTES", "issn_l": "2079-1690", "issn": ["2079-1690", "2687-0290"], "is_oa": true, "is_in_doaj": false, "is_indexed_in_scopus": false, "is_core": false, "host_organization": null, "host_organization_name": null, "host_organization_lineage": [], "host_organization_lineage_names": [], "type": "journal"}, "license": null, "license_id": null, "version": "publishedVersion", "is_accepted": true, "is_published": true}], "best_oa_location": {"is_oa": true, "landing_page_url": "https://doi.org/10.22394/2079-1690-2022-1-3-98-105", "pdf_url": null, "source": {"id": "https://openalex.org/S4210176877", "display_name": "STATE AND MUNICIPAL MANAGEMENT SCHOLAR NOTES", "issn_l": "2079-1690", "issn": ["2079-1690", "2687-0290"], "is_oa": true, "is_in_doaj": false, "is_indexed_in_scopus": false, "is_core": false, "host_organization": null, "host_organization_name": null, "host_organization_lineage": [], "host_organization_lineage_names": [], "type": "journal"}, "license": null, "license_id": null, "version": "publishedVersion", "is_accepted": true, "is_published": true}, "sustainable_development_goals": [{"id": "https://metadata.un.org/sdg/8", "score": 0.71, "display_name": "Decent work and economic growth"}], "grants": [], "datasets": [], "versions": [], "referenced_works_count": 0, "referenced_works": [], "related_works": ["https://openalex.org/W4372016010", "https://openalex.org/W4372015973", "https://openalex.org/W4240794930", "https://openalex.org/W4230693165", "https://openalex.org/W3002838864", "https://openalex.org/W2377832899", "https://openalex.org/W2375373054", "https://openalex.org/W2354324885", "https://openalex.org/W2354021329", "https://openalex.org/W1534687187"], "abstract_inverted_index": {"The": [0], "specifics": [1, 62], "of": [2, 5, 8, 20, 23, 25, 54, 63, 80, 87, 101, 103, 106], "the": [3, 6, 9, 17, 37, 41, 55, 67, 73, 75, 78, 85, 93, 98, 104], "development": [4], "economy": [7], "Russian": [10], "Federation": [11], "is": [12, 36, 57], "its": [13, 60], "diversity,": [14], "which": [15], "implies": [16], "simultaneous": [18], "existence": [19], "different": [21, 28], "subordinations": [22], "factors": [24, 71, 105], "production": [26, 70, 107], "in": [27, 31, 40, 72, 84, 97], "regions.": [29], "So,": [30], "Stavropol": [32, 49], "and": [33, 48], "Ingushetia,": [34], "capital": [35], "dominant": [38], "factor,": [39], "Rostov": [42], "region": [43], "\u2013": [44, 50], "land,": [45], "Krasnodar": [46], "Krai": [47], "labor.": [51], "Consequently,": [52], "each": [53, 102], "subjects": [56], "characterized": [58], "by": [59], "own": [61], "investment.": [64], "To": [65], "display": [66], "connections": [68], "between": [69], "farm,": [74], "article": [76], "uses": [77], "matrices": [79], "public": [81], "reproduction": [82], "presented": [83, 94], "concept": [86], "I.": [88], "R.": [89], "Bugayan.": [90], "Based": [91], "on": [92], "data,": [95], "patterns": [96], "investment": [99], "features": [100], "are": [108], "noted.": [109]}, "abstract_inverted_index_v3": null, "cited_by_api_url": "https://api.openalex.org/works?filter=cites:W4304161328", "counts_by_year": [{"year": 2024, "cited_by_count": 1}], "updated_date": "2025-06-23T08:05:01.297653", "created_date": "2022-10-11"}