{"id": "https://openalex.org/W4317718199", "doi": "https://doi.org/10.1007/s12053-023-10084-x", "title": "Impact of ground source heat pumps on house sales prices in Finland", "display_name": "Impact of ground source heat pumps on house sales prices in Finland", "publication_year": 2023, "publication_date": "2023-01-23", "ids": {"openalex": "https://openalex.org/W4317718199", "doi": "https://doi.org/10.1007/s12053-023-10084-x"}, "language": "en", "primary_location": {"is_oa": true, "landing_page_url": "https://doi.org/10.1007/s12053-023-10084-x", "pdf_url": "https://link.springer.com/content/pdf/10.1007/s12053-023-10084-x.pdf", "source": {"id": "https://openalex.org/S133853345", "display_name": "Energy Efficiency", "issn_l": "1570-646X", "issn": ["1570-646X", "1570-6478"], "is_oa": false, "is_in_doaj": false, "is_indexed_in_scopus": true, "is_core": true, "host_organization": "https://openalex.org/P4310319900", "host_organization_name": "Springer Science+Business Media", "host_organization_lineage": ["https://openalex.org/P4310319965", "https://openalex.org/P4310319900"], "host_organization_lineage_names": ["Springer Nature", "Springer Science+Business Media"], "type": "journal"}, "license": "cc-by", "license_id": "https://openalex.org/licenses/cc-by", "version": "publishedVersion", "is_accepted": true, "is_published": true}, "type": "article", "type_crossref": "journal-article", "indexed_in": ["crossref"], "open_access": {"is_oa": true, "oa_status": "hybrid", "oa_url": "https://link.springer.com/content/pdf/10.1007/s12053-023-10084-x.pdf", "any_repository_has_fulltext": false}, "authorships": [{"author_position": "first", "author": {"id": "https://openalex.org/A5046962148", "display_name": "Jussi Vimpari", "orcid": "https://orcid.org/0000-0002-0592-9826"}, "institutions": [{"id": "https://openalex.org/I9927081", "display_name": "Aalto University", "ror": "https://ror.org/020hwjq30", "country_code": "FI", "type": "funder", "lineage": ["https://openalex.org/I9927081"]}], "countries": ["FI"], "is_corresponding": true, "raw_author_name": "Jussi Vimpari", "raw_affiliation_strings": ["Department of Built Environment, Real Estate Economics, Aalto University, P.O. Box 11000 (Otakaari 1B), Aalto, FI-00076, Espoo, Finland"], "affiliations": [{"raw_affiliation_string": "Department of Built Environment, Real Estate Economics, Aalto University, P.O. Box 11000 (Otakaari 1B), Aalto, FI-00076, Espoo, Finland", "institution_ids": ["https://openalex.org/I9927081"]}]}], "institution_assertions": [], "countries_distinct_count": 1, "institutions_distinct_count": 1, "corresponding_author_ids": ["https://openalex.org/A5046962148"], "corresponding_institution_ids": ["https://openalex.org/I9927081"], "apc_list": {"value": 2390, "currency": "EUR", "value_usd": 2990}, "apc_paid": {"value": 2390, "currency": "EUR", "value_usd": 2990}, "fwci": 0.435, "has_fulltext": true, "fulltext_origin": "pdf", "cited_by_count": 2, "citation_normalized_percentile": {"value": 0.465026, "is_in_top_1_percent": false, "is_in_top_10_percent": false}, "cited_by_percentile_year": {"min": 75, "max": 81}, "biblio": {"volume": "16", "issue": "2", "first_page": null, "last_page": null}, "is_retracted": false, "is_paratext": false, "primary_topic": {"id": "https://openalex.org/T10121", "display_name": "Building Energy and Comfort Optimization", "score": 0.9955, "subfield": {"id": "https://openalex.org/subfields/2215", "display_name": "Building and Construction"}, "field": {"id": "https://openalex.org/fields/22", "display_name": "Engineering"}, "domain": {"id": "https://openalex.org/domains/3", "display_name": "Physical Sciences"}}, "topics": [{"id": "https://openalex.org/T10121", "display_name": "Building Energy and Comfort Optimization", "score": 0.9955, "subfield": {"id": "https://openalex.org/subfields/2215", "display_name": "Building and Construction"}, "field": {"id": "https://openalex.org/fields/22", "display_name": "Engineering"}, "domain": {"id": "https://openalex.org/domains/3", "display_name": "Physical Sciences"}}, {"id": "https://openalex.org/T10632", "display_name": "Housing Market and Economics", "score": 0.9948, "subfield": {"id": "https://openalex.org/subfields/2002", "display_name": "Economics and Econometrics"}, "field": {"id": "https://openalex.org/fields/20", "display_name": "Economics, Econometrics and Finance"}, "domain": {"id": "https://openalex.org/domains/2", "display_name": "Social Sciences"}}, {"id": "https://openalex.org/T11988", "display_name": "Sustainable Building Design and Assessment", "score": 0.9913, "subfield": {"id": "https://openalex.org/subfields/2215", "display_name": "Building and Construction"}, "field": {"id": "https://openalex.org/fields/22", "display_name": "Engineering"}, "domain": {"id": "https://openalex.org/domains/3", "display_name": "Physical Sciences"}}], "keywords": [{"id": "https://openalex.org/keywords/investment", "display_name": "Investment", "score": 0.5197708}, {"id": "https://openalex.org/keywords/capital-investment", "display_name": "Capital investment", "score": 0.41755697}, {"id": "https://openalex.org/keywords/capital-expenditure", "display_name": "Capital expenditure", "score": 0.41585138}], "concepts": [{"id": "https://openalex.org/C158739034", "wikidata": "https://www.wikidata.org/wiki/Q1907114", "display_name": "Metropolitan area", "level": 2, "score": 0.57423484}, {"id": "https://openalex.org/C27548731", "wikidata": "https://www.wikidata.org/wiki/Q88272", "display_name": "Investment (military)", "level": 3, "score": 0.5197708}, {"id": "https://openalex.org/C2779343474", "wikidata": "https://www.wikidata.org/wiki/Q3109175", "display_name": "Context (archaeology)", "level": 2, "score": 0.50540185}, {"id": "https://openalex.org/C162324750", "wikidata": "https://www.wikidata.org/wiki/Q8134", "display_name": "Economics", "level": 0, "score": 0.457185}, {"id": "https://openalex.org/C144133560", "wikidata": "https://www.wikidata.org/wiki/Q4830453", "display_name": "Business", "level": 0, "score": 0.45618334}, {"id": "https://openalex.org/C2776461528", "wikidata": "https://www.wikidata.org/wiki/Q131313", "display_name": "Heat pump", "level": 3, "score": 0.4481765}, {"id": "https://openalex.org/C182306322", "wikidata": "https://www.wikidata.org/wiki/Q1779371", "display_name": "Order (exchange)", "level": 2, "score": 0.42807347}, {"id": "https://openalex.org/C2985722716", "wikidata": "https://www.wikidata.org/wiki/Q4290", "display_name": "Capital investment", "level": 2, "score": 0.41755697}, {"id": "https://openalex.org/C172497479", "wikidata": "https://www.wikidata.org/wiki/Q302208", "display_name": "Capital expenditure", "level": 2, "score": 0.41585138}, {"id": "https://openalex.org/C48824518", "wikidata": "https://www.wikidata.org/wiki/Q396340", "display_name": "Agricultural economics", "level": 1, "score": 0.40839198}, {"id": "https://openalex.org/C175605778", "wikidata": "https://www.wikidata.org/wiki/Q3299701", "display_name": "Natural resource economics", "level": 1, "score": 0.32526875}, {"id": "https://openalex.org/C10138342", "wikidata": "https://www.wikidata.org/wiki/Q43015", "display_name": "Finance", "level": 1, "score": 0.2354854}, {"id": "https://openalex.org/C127413603", "wikidata": "https://www.wikidata.org/wiki/Q11023", "display_name": "Engineering", "level": 0, "score": 0.16941553}, {"id": "https://openalex.org/C205649164", "wikidata": "https://www.wikidata.org/wiki/Q1071", "display_name": "Geography", "level": 0, "score": 0.12432349}, {"id": "https://openalex.org/C78519656", "wikidata": "https://www.wikidata.org/wiki/Q101333", "display_name": "Mechanical engineering", "level": 1, "score": 0.0}, {"id": "https://openalex.org/C107706546", "wikidata": "https://www.wikidata.org/wiki/Q189124", "display_name": "Heat exchanger", "level": 2, "score": 0.0}, {"id": "https://openalex.org/C166957645", "wikidata": "https://www.wikidata.org/wiki/Q23498", "display_name": "Archaeology", "level": 1, "score": 0.0}, {"id": "https://openalex.org/C94625758", "wikidata": "https://www.wikidata.org/wiki/Q7163", "display_name": "Politics", "level": 2, "score": 0.0}, {"id": "https://openalex.org/C17744445", "wikidata": "https://www.wikidata.org/wiki/Q36442", "display_name": "Political science", "level": 0, "score": 0.0}, {"id": "https://openalex.org/C199539241", "wikidata": "https://www.wikidata.org/wiki/Q7748", "display_name": "Law", "level": 1, "score": 0.0}], "mesh": [], "locations_count": 1, "locations": [{"is_oa": true, "landing_page_url": "https://doi.org/10.1007/s12053-023-10084-x", "pdf_url": "https://link.springer.com/content/pdf/10.1007/s12053-023-10084-x.pdf", "source": {"id": "https://openalex.org/S133853345", "display_name": "Energy Efficiency", "issn_l": "1570-646X", "issn": ["1570-646X", "1570-6478"], "is_oa": false, "is_in_doaj": false, "is_indexed_in_scopus": true, "is_core": true, "host_organization": "https://openalex.org/P4310319900", "host_organization_name": "Springer Science+Business Media", "host_organization_lineage": ["https://openalex.org/P4310319965", "https://openalex.org/P4310319900"], "host_organization_lineage_names": ["Springer Nature", "Springer Science+Business Media"], "type": "journal"}, "license": "cc-by", "license_id": "https://openalex.org/licenses/cc-by", "version": "publishedVersion", "is_accepted": true, "is_published": true}], "best_oa_location": {"is_oa": true, "landing_page_url": "https://doi.org/10.1007/s12053-023-10084-x", "pdf_url": "https://link.springer.com/content/pdf/10.1007/s12053-023-10084-x.pdf", "source": {"id": "https://openalex.org/S133853345", "display_name": "Energy Efficiency", "issn_l": "1570-646X", "issn": ["1570-646X", "1570-6478"], "is_oa": false, "is_in_doaj": false, "is_indexed_in_scopus": true, "is_core": true, "host_organization": "https://openalex.org/P4310319900", "host_organization_name": "Springer Science+Business Media", "host_organization_lineage": ["https://openalex.org/P4310319965", "https://openalex.org/P4310319900"], "host_organization_lineage_names": ["Springer Nature", "Springer Science+Business Media"], "type": "journal"}, "license": "cc-by", "license_id": "https://openalex.org/licenses/cc-by", "version": "publishedVersion", "is_accepted": true, "is_published": true}, "sustainable_development_goals": [{"score": 0.66, "display_name": "Affordable and clean energy", "id": "https://metadata.un.org/sdg/7"}], "grants": [{"funder": "https://openalex.org/F4320321108", "funder_display_name": "Academy of Finland", "award_id": "Smart land use policy for sustainable urbanization"}, {"funder": "https://openalex.org/F4320321394", "funder_display_name": "Aalto-Yliopisto", "award_id": null}], "datasets": [], "versions": [], "referenced_works_count": 16, "referenced_works": ["https://openalex.org/W1568840751", "https://openalex.org/W1973396628", "https://openalex.org/W2025352602", "https://openalex.org/W2051688880", "https://openalex.org/W2052171425", "https://openalex.org/W2061717395", "https://openalex.org/W2104006915", "https://openalex.org/W2150258813", "https://openalex.org/W2515912751", "https://openalex.org/W2734428005", "https://openalex.org/W3044630931", "https://openalex.org/W3123148488", "https://openalex.org/W3124378774", "https://openalex.org/W3124765604", "https://openalex.org/W3125142666", "https://openalex.org/W3161762549"], "related_works": ["https://openalex.org/W4391481557", "https://openalex.org/W4292064814", "https://openalex.org/W4241249735", "https://openalex.org/W2369981844", "https://openalex.org/W2360863633", "https://openalex.org/W2352053010", "https://openalex.org/W2347835431", "https://openalex.org/W2160461211", "https://openalex.org/W2079915993", "https://openalex.org/W1595518739"], "abstract_inverted_index": {"Abstract": [0], "Buildings": [1], "contribute": [2], "to": [3, 64, 81, 193, 201, 210], "approximately": [4], "28%": [5], "of": [6, 21, 47, 53, 58, 86, 96, 113, 127, 150, 167, 174], "global": [7], "energy-related": [8], "emissions.": [9], "Heat": [10], "pumps": [11, 30], "are": [12, 33, 170, 208], "a": [13, 108, 151, 190], "key": [14], "technology": [15], "for": [16, 40, 103, 189], "decarbonising": [17], "the": [18, 44, 83, 93, 122, 125, 139, 146, 155, 175, 184, 195], "heating": [19, 90], "emissions": [20], "buildings.": [22], "This": [23, 198], "study": [24], "focuses": [25], "on": [26, 71, 115, 172], "ground": [27], "source": [28], "heat": [29, 214], "(GSHP),": [31], "which": [32], "increasingly": [34], "used": [35], "in": [36, 124, 130, 133, 138, 160, 163, 178, 213], "colder": [37], "regions.": [38], "Since,": [39], "an": [41, 51, 69], "average": [42, 136], "home,": [43], "capital": [45, 148], "expenditure": [46, 149], "GSHP": [48, 67, 106, 152], "can": [49], "be": [50, 187], "order": [52], "magnitude": [54], "higher": [55], "than": [56], "that": [57, 102], "traditional": [59], "heating,": [60], "it": [61], "is": [62, 92, 199], "important": [63, 200], "understand": [65, 202], "whether": [66], "has": [68], "impact": [70, 112], "house": [72, 116, 137, 185], "transaction": [73], "prices.": [74, 118], "A": [75], "hedonic": [76, 99], "price": [77, 157], "model": [78], "was": [79], "constructed": [80], "estimate": [82], "sales": [84, 117, 156], "prices": [85, 129], "detached": [87, 104], "houses,": [88, 105], "where": [89], "type": [91], "main": [94], "variable": [95], "interest.": [97], "The": [98], "analysis": [100, 120], "revealed": [101], "had": [107], "statistically": [109], "significant": [110], "positive": [111], "5.33%": [114], "Further": [119], "puts": [121], "premium": [123], "context": [126], "housing": [128, 182], "different": [131], "locations": [132, 179], "Finland.": [134], "An": [135], "Helsinki": [140], "Metropolitan": [141], "Area": [142], "(HMA)": [143], "could": [144], "cover": [145], "required": [147, 171], "system": [153], "with": [154, 180], "premium,": [158], "whereas": [159], "other": [161], "areas": [162], "Finland,": [164], "5": [165], "years": [166], "energy": [168, 205], "savings": [169], "top": [173], "premium.": [176], "Hence,": [177], "lower": [181], "prices,": [183], "must": [186], "owned": [188], "longer": [191], "period": [192], "recoup": [194], "investment": [196], "costs.": [197], "when": [203], "national": [204], "aid": [206], "policies": [207], "planned": [209], "accelerate": [211], "investments": [212], "pumps.": [215]}, "abstract_inverted_index_v3": null, "cited_by_api_url": "https://api.openalex.org/works?filter=cites:W4317718199", "counts_by_year": [{"year": 2024, "cited_by_count": 2}], "updated_date": "2025-06-17T09:19:04.559091", "created_date": "2023-01-23"}