{"id": "https://openalex.org/W4381736306", "doi": "https://doi.org/10.26425/1816-4277-2023-5-131-140", "title": "On the comparative assessment of the investments\u2019 economic efficiency in production capital", "display_name": "On the comparative assessment of the investments\u2019 economic efficiency in production capital", "publication_year": 2023, "publication_date": "2023-06-22", "ids": {"openalex": "https://openalex.org/W4381736306", "doi": "https://doi.org/10.26425/1816-4277-2023-5-131-140"}, "language": "en", "primary_location": {"is_oa": true, "landing_page_url": "https://doi.org/10.26425/1816-4277-2023-5-131-140", "pdf_url": "https://vestnik.guu.ru/jour/article/download/4499/2692", "source": {"id": "https://openalex.org/S4210225429", "display_name": "Vestnik Universiteta", "issn_l": "1816-4277", "issn": ["1816-4277", "2686-8415"], "is_oa": true, "is_in_doaj": true, "is_indexed_in_scopus": false, "is_core": false, "host_organization": "https://openalex.org/P4310312746", "host_organization_name": "Saint Petersburg State University", "host_organization_lineage": ["https://openalex.org/P4310312746"], "host_organization_lineage_names": ["Saint Petersburg State University"], "type": "journal"}, "license": "cc-by", "license_id": "https://openalex.org/licenses/cc-by", "version": "publishedVersion", "is_accepted": true, "is_published": true}, "type": "article", "type_crossref": "journal-article", "indexed_in": ["crossref"], "open_access": {"is_oa": true, "oa_status": "diamond", "oa_url": "https://vestnik.guu.ru/jour/article/download/4499/2692", "any_repository_has_fulltext": false}, "authorships": [{"author_position": "first", "author": {"id": "https://openalex.org/A5075640071", "display_name": "Viktor Serov", "orcid": "https://orcid.org/0000-0001-5143-1896"}, "institutions": [{"id": "https://openalex.org/I111567634", "display_name": "State University of Management", "ror": "https://ror.org/00nxz6d14", "country_code": "RU", "type": "education", "lineage": ["https://openalex.org/I111567634"]}], "countries": ["RU"], "is_corresponding": false, "raw_author_name": "V. M. Serov", "raw_affiliation_strings": ["State University of Management"], "affiliations": [{"raw_affiliation_string": "State University of Management", "institution_ids": ["https://openalex.org/I111567634"]}]}, {"author_position": "last", "author": {"id": "https://openalex.org/A5006460419", "display_name": "Yu. P. Tikhonov", "orcid": "https://orcid.org/0000-0003-2819-6394"}, "institutions": [{"id": "https://openalex.org/I111567634", "display_name": "State University of Management", "ror": "https://ror.org/00nxz6d14", "country_code": "RU", "type": "education", "lineage": ["https://openalex.org/I111567634"]}], "countries": ["RU"], "is_corresponding": false, "raw_author_name": "Yu. P. Tikhonov", "raw_affiliation_strings": ["State University of Management"], "affiliations": [{"raw_affiliation_string": "State University of Management", "institution_ids": ["https://openalex.org/I111567634"]}]}], "institution_assertions": [], "countries_distinct_count": 1, "institutions_distinct_count": 1, "corresponding_author_ids": [], "corresponding_institution_ids": [], "apc_list": {"value": 0, "currency": "USD", "value_usd": 0}, "apc_paid": null, "fwci": 0.588, "has_fulltext": true, "fulltext_origin": "pdf", "cited_by_count": 2, "citation_normalized_percentile": {"value": 0.510349, "is_in_top_1_percent": false, "is_in_top_10_percent": false}, "cited_by_percentile_year": {"min": 75, "max": 81}, "biblio": {"volume": null, "issue": "5", "first_page": "131", "last_page": "140"}, "is_retracted": false, "is_paratext": false, "primary_topic": {"id": "https://openalex.org/T13190", "display_name": "Engineering and Environmental Studies", "score": 0.8939, "subfield": {"id": "https://openalex.org/subfields/2212", "display_name": "Ocean Engineering"}, "field": {"id": "https://openalex.org/fields/22", "display_name": "Engineering"}, "domain": {"id": "https://openalex.org/domains/3", "display_name": "Physical Sciences"}}, "topics": [{"id": "https://openalex.org/T13190", "display_name": "Engineering and Environmental Studies", "score": 0.8939, "subfield": {"id": "https://openalex.org/subfields/2212", "display_name": "Ocean Engineering"}, "field": {"id": "https://openalex.org/fields/22", "display_name": "Engineering"}, "domain": {"id": "https://openalex.org/domains/3", "display_name": "Physical Sciences"}}, {"id": "https://openalex.org/T13181", "display_name": "Economic and Technological Systems Analysis", "score": 0.8591, "subfield": {"id": "https://openalex.org/subfields/1405", "display_name": "Management of Technology and Innovation"}, "field": {"id": "https://openalex.org/fields/14", "display_name": "Business, Management and Accounting"}, "domain": {"id": "https://openalex.org/domains/2", "display_name": "Social Sciences"}}, {"id": "https://openalex.org/T13547", "display_name": "Economic and Industrial Development", "score": 0.8554, "subfield": {"id": "https://openalex.org/subfields/2002", "display_name": "Economics and Econometrics"}, "field": {"id": "https://openalex.org/fields/20", "display_name": "Economics, Econometrics and Finance"}, "domain": {"id": "https://openalex.org/domains/2", "display_name": "Social Sciences"}}], "keywords": [{"id": "https://openalex.org/keywords/investment", "display_name": "Investment", "score": 0.7109316}, {"id": "https://openalex.org/keywords/capital", "display_name": "Capital (architecture)", "score": 0.5853111}, {"id": "https://openalex.org/keywords/capital-investment", "display_name": "Capital investment", "score": 0.56321234}, {"id": "https://openalex.org/keywords/factors-of-production", "display_name": "Factors of production", "score": 0.44958}, {"id": "https://openalex.org/keywords/capital-budgeting", "display_name": "Capital Budgeting", "score": 0.42708212}, {"id": "https://openalex.org/keywords/economic-efficiency", "display_name": "Economic Efficiency", "score": 0.41342258}], "concepts": [{"id": "https://openalex.org/C2778348673", "wikidata": "https://www.wikidata.org/wiki/Q739302", "display_name": "Production (economics)", "level": 2, "score": 0.7293948}, {"id": "https://openalex.org/C27548731", "wikidata": "https://www.wikidata.org/wiki/Q88272", "display_name": "Investment (military)", "level": 3, "score": 0.7109316}, {"id": "https://openalex.org/C83646750", "wikidata": "https://www.wikidata.org/wiki/Q193893", "display_name": "Capital (architecture)", "level": 2, "score": 0.5853111}, {"id": "https://openalex.org/C98045186", "wikidata": "https://www.wikidata.org/wiki/Q205663", "display_name": "Process (computing)", "level": 2, "score": 0.58228695}, {"id": "https://openalex.org/C2778137410", "wikidata": "https://www.wikidata.org/wiki/Q2732820", "display_name": "Government (linguistics)", "level": 2, "score": 0.575977}, {"id": "https://openalex.org/C2985722716", "wikidata": "https://www.wikidata.org/wiki/Q4290", "display_name": "Capital investment", "level": 2, "score": 0.56321234}, {"id": "https://openalex.org/C40700", "wikidata": "https://www.wikidata.org/wiki/Q1411783", "display_name": "Industrial organization", "level": 1, "score": 0.47682112}, {"id": "https://openalex.org/C16927522", "wikidata": "https://www.wikidata.org/wiki/Q210947", "display_name": "Factors of production", "level": 3, "score": 0.44958}, {"id": "https://openalex.org/C144133560", "wikidata": "https://www.wikidata.org/wiki/Q4830453", "display_name": "Business", "level": 0, "score": 0.44926733}, {"id": "https://openalex.org/C162324750", "wikidata": "https://www.wikidata.org/wiki/Q8134", "display_name": "Economics", "level": 0, "score": 0.44264802}, {"id": "https://openalex.org/C57918260", "wikidata": "https://www.wikidata.org/wiki/Q1354666", "display_name": "Capital budgeting", "level": 3, "score": 0.42708212}, {"id": "https://openalex.org/C76474335", "wikidata": "https://www.wikidata.org/wiki/Q215551", "display_name": "Comparative advantage", "level": 2, "score": 0.41401613}, {"id": "https://openalex.org/C109332788", "wikidata": "https://www.wikidata.org/wiki/Q615445", "display_name": "Economic efficiency", "level": 2, "score": 0.41342258}, {"id": "https://openalex.org/C112930515", "wikidata": "https://www.wikidata.org/wiki/Q4389547", "display_name": "Risk analysis (engineering)", "level": 1, "score": 0.34446907}, {"id": "https://openalex.org/C10138342", "wikidata": "https://www.wikidata.org/wiki/Q43015", "display_name": "Finance", "level": 1, "score": 0.26392442}, {"id": "https://openalex.org/C41008148", "wikidata": "https://www.wikidata.org/wiki/Q21198", "display_name": "Computer science", "level": 0, "score": 0.2279146}, {"id": "https://openalex.org/C175444787", "wikidata": "https://www.wikidata.org/wiki/Q39072", "display_name": "Microeconomics", "level": 1, "score": 0.21320355}, {"id": "https://openalex.org/C155202549", "wikidata": "https://www.wikidata.org/wiki/Q178803", "display_name": "International trade", "level": 1, "score": 0.075253725}, {"id": "https://openalex.org/C41895202", "wikidata": "https://www.wikidata.org/wiki/Q8162", "display_name": "Linguistics", "level": 1, "score": 0.0}, {"id": "https://openalex.org/C138885662", "wikidata": "https://www.wikidata.org/wiki/Q5891", "display_name": "Philosophy", "level": 0, "score": 0.0}, {"id": "https://openalex.org/C166957645", "wikidata": "https://www.wikidata.org/wiki/Q23498", "display_name": "Archaeology", "level": 1, "score": 0.0}, {"id": "https://openalex.org/C94625758", "wikidata": "https://www.wikidata.org/wiki/Q7163", "display_name": "Politics", "level": 2, "score": 0.0}, {"id": "https://openalex.org/C21425071", "wikidata": "https://www.wikidata.org/wiki/Q7249389", "display_name": "Project appraisal", "level": 2, "score": 0.0}, {"id": "https://openalex.org/C17744445", "wikidata": "https://www.wikidata.org/wiki/Q36442", "display_name": "Political science", "level": 0, "score": 0.0}, {"id": "https://openalex.org/C199539241", "wikidata": "https://www.wikidata.org/wiki/Q7748", "display_name": "Law", "level": 1, "score": 0.0}, {"id": "https://openalex.org/C95457728", "wikidata": "https://www.wikidata.org/wiki/Q309", "display_name": "History", "level": 0, "score": 0.0}, {"id": "https://openalex.org/C111919701", "wikidata": "https://www.wikidata.org/wiki/Q9135", "display_name": "Operating system", "level": 1, "score": 0.0}], "mesh": [], "locations_count": 1, "locations": [{"is_oa": true, "landing_page_url": "https://doi.org/10.26425/1816-4277-2023-5-131-140", "pdf_url": "https://vestnik.guu.ru/jour/article/download/4499/2692", "source": {"id": "https://openalex.org/S4210225429", "display_name": "Vestnik Universiteta", "issn_l": "1816-4277", "issn": ["1816-4277", "2686-8415"], "is_oa": true, "is_in_doaj": true, "is_indexed_in_scopus": false, "is_core": false, "host_organization": "https://openalex.org/P4310312746", "host_organization_name": "Saint Petersburg State University", "host_organization_lineage": ["https://openalex.org/P4310312746"], "host_organization_lineage_names": ["Saint Petersburg State University"], "type": "journal"}, "license": "cc-by", "license_id": "https://openalex.org/licenses/cc-by", "version": "publishedVersion", "is_accepted": true, "is_published": true}], "best_oa_location": {"is_oa": true, "landing_page_url": "https://doi.org/10.26425/1816-4277-2023-5-131-140", "pdf_url": "https://vestnik.guu.ru/jour/article/download/4499/2692", "source": {"id": "https://openalex.org/S4210225429", "display_name": "Vestnik Universiteta", "issn_l": "1816-4277", "issn": ["1816-4277", "2686-8415"], "is_oa": true, "is_in_doaj": true, "is_indexed_in_scopus": false, "is_core": false, "host_organization": "https://openalex.org/P4310312746", "host_organization_name": "Saint Petersburg State University", "host_organization_lineage": ["https://openalex.org/P4310312746"], "host_organization_lineage_names": ["Saint Petersburg State University"], "type": "journal"}, "license": "cc-by", "license_id": "https://openalex.org/licenses/cc-by", "version": "publishedVersion", "is_accepted": true, "is_published": true}, "sustainable_development_goals": [], "grants": [], "datasets": [], "versions": [], "referenced_works_count": 0, "referenced_works": [], "related_works": ["https://openalex.org/W575988719", "https://openalex.org/W572710838", "https://openalex.org/W4230710322", "https://openalex.org/W2482608795", "https://openalex.org/W2358093750", "https://openalex.org/W2103113759", "https://openalex.org/W2070446437", "https://openalex.org/W1974815045", "https://openalex.org/W1512526712", "https://openalex.org/W1028691542"], "abstract_inverted_index": {"The": [0, 51, 93], "article": [1], "notes": [2], "that": [3], "in": [4, 34, 71], "the": [5, 15, 28, 35, 44, 73, 80, 120], "current": [6], "methodological": [7], "document": [8], "approved": [9], "by": [10], "government": [11], "bodies": [12], "on": [13, 119], "determining": [14, 72], "investment": [16, 38, 77, 111], "projects": [17, 78, 112], "effectiveness": [18], "there": [19], "are": [20, 58, 98], "no": [21], "recommendations": [22], "for": [23, 79, 133], "a": [24, 106, 114], "comparative": [25, 107], "assessment": [26, 108], "of": [27, 31, 37, 76, 82, 90, 109, 122], "economic": [29, 74], "efficiency": [30, 75], "decisions": [32, 118], "made": [33], "process": [36], "and": [39, 42, 60, 68, 87, 96, 116, 126, 130, 135], "construction": [40, 131], "activities,": [41], "at": [43], "same": [45], "time": [46], "their": [47], "necessity": [48], "is": [49, 63], "shown.": [50], "authors\u2019": [52], "approaches": [53, 70], "to": [54, 65, 104], "solving": [55], "this": [56], "problem": [57], "substantiated": [59], "presented.": [61], "It": [62], "proposed": [64, 94], "use": [66], "income": [67], "property": [69], "creation": [81], "new": [83], "enterprises,": [84], "industries,": [85], "reconstruction": [86], "technical": [88], "re-equipment": [89], "existing": [91], "ones.": [92], "methods": [95], "indicators": [97], "presented,": [99], "which": [100], "make": [101], "it": [102], "possible": [103], "give": [105], "both": [110], "as": [113], "whole": [115], "individual": [117], "choice": [121], "production": [123], "technologies,": [124], "technological": [125], "other": [127], "equipment,": [128], "design": [129], "solutions": [132], "buildings": [134], "structures.": [136]}, "abstract_inverted_index_v3": null, "cited_by_api_url": "https://api.openalex.org/works?filter=cites:W4381736306", "counts_by_year": [{"year": 2024, "cited_by_count": 2}], "updated_date": "2025-06-22T23:32:06.983091", "created_date": "2023-06-24"}