{"id": "https://openalex.org/W4389938214", "doi": "https://doi.org/10.32782/2523-4803/73-3-2", "title": "THE PROBLEM OF ENSURING A HIGH LEVEL OF INVESTMENT ATTRACTIVENESS IN THE REGIONS OF UKRAINE: PRACTICAL RECOMMENDATIONS", "display_name": "THE PROBLEM OF ENSURING A HIGH LEVEL OF INVESTMENT ATTRACTIVENESS IN THE REGIONS OF UKRAINE: PRACTICAL RECOMMENDATIONS", "publication_year": 2023, "publication_date": "2023-01-01", "ids": {"openalex": "https://openalex.org/W4389938214", "doi": "https://doi.org/10.32782/2523-4803/73-3-2"}, "language": "en", "primary_location": {"is_oa": true, "landing_page_url": "https://doi.org/10.32782/2523-4803/73-3-2", "pdf_url": null, "source": {"id": "https://openalex.org/S4210181594", "display_name": "Scientific Notes of Taurida National V I Vernadsky University Series Economy and Management", "issn_l": "2523-4803", "issn": ["2523-4803", "2707-1103"], "is_oa": true, "is_in_doaj": false, "is_indexed_in_scopus": false, "is_core": false, "host_organization": null, "host_organization_name": null, "host_organization_lineage": [], "host_organization_lineage_names": [], "type": "journal"}, "license": null, "license_id": null, "version": "publishedVersion", "is_accepted": true, "is_published": true}, "type": "article", "type_crossref": "journal-article", "indexed_in": ["crossref"], "open_access": {"is_oa": true, "oa_status": "gold", "oa_url": "https://doi.org/10.32782/2523-4803/73-3-2", "any_repository_has_fulltext": false}, "authorships": [{"author_position": "first", "author": {"id": "https://openalex.org/A5049301347", "display_name": "\u041e. \u041f. \u0410\u0442\u0430\u043c\u0430\u0441", "orcid": null}, "institutions": [{"id": "https://openalex.org/I3019264281", "display_name": "Dnipro State Agrarian and Economic University", "ror": "https://ror.org/01s5n0596", "country_code": "UA", "type": "education", "lineage": ["https://openalex.org/I3019264281"]}], "countries": ["UA"], "is_corresponding": true, "raw_author_name": "Oleksandr \u0410tamas", "raw_affiliation_strings": ["Dnipro State Agrarian and Economic University"], "affiliations": [{"raw_affiliation_string": "Dnipro State Agrarian and Economic University", "institution_ids": ["https://openalex.org/I3019264281"]}]}], "institution_assertions": [], "countries_distinct_count": 1, "institutions_distinct_count": 1, "corresponding_author_ids": ["https://openalex.org/A5049301347"], "corresponding_institution_ids": ["https://openalex.org/I3019264281"], "apc_list": null, "apc_paid": null, "fwci": 0.0, "has_fulltext": true, "fulltext_origin": "pdf", "cited_by_count": 0, "citation_normalized_percentile": {"value": 0.0, "is_in_top_1_percent": false, "is_in_top_10_percent": false}, "cited_by_percentile_year": {"min": 0, "max": 64}, "biblio": {"volume": "73", "issue": "3", "first_page": null, "last_page": null}, "is_retracted": false, "is_paratext": false, "primary_topic": {"id": "https://openalex.org/T13172", "display_name": "Economic Issues in Ukraine", "score": 0.9963, "subfield": {"id": "https://openalex.org/subfields/2000", "display_name": "General Economics, Econometrics and Finance"}, "field": {"id": "https://openalex.org/fields/20", "display_name": "Economics, Econometrics and Finance"}, "domain": {"id": "https://openalex.org/domains/2", "display_name": "Social Sciences"}}, "topics": [{"id": "https://openalex.org/T13172", "display_name": "Economic Issues in Ukraine", "score": 0.9963, "subfield": {"id": "https://openalex.org/subfields/2000", "display_name": "General Economics, Econometrics and Finance"}, "field": {"id": "https://openalex.org/fields/20", "display_name": "Economics, Econometrics and Finance"}, "domain": {"id": "https://openalex.org/domains/2", "display_name": "Social Sciences"}}, {"id": "https://openalex.org/T12922", "display_name": "Business and Economic Development", "score": 0.9883, "subfield": {"id": "https://openalex.org/subfields/2308", "display_name": "Management, Monitoring, Policy and Law"}, "field": {"id": "https://openalex.org/fields/23", "display_name": "Environmental Science"}, "domain": {"id": "https://openalex.org/domains/3", "display_name": "Physical Sciences"}}, {"id": "https://openalex.org/T13411", "display_name": "Labor Market and Education", "score": 0.9815, "subfield": {"id": "https://openalex.org/subfields/2002", "display_name": "Economics and Econometrics"}, "field": {"id": "https://openalex.org/fields/20", "display_name": "Economics, Econometrics and Finance"}, "domain": {"id": "https://openalex.org/domains/2", "display_name": "Social Sciences"}}], "keywords": [{"id": "https://openalex.org/keywords/investment", "display_name": "Investment", "score": 0.75857925}, {"id": "https://openalex.org/keywords/capital", "display_name": "Capital (architecture)", "score": 0.5948087}, {"id": "https://openalex.org/keywords/capital-investment", "display_name": "Capital investment", "score": 0.4225284}], "concepts": [{"id": "https://openalex.org/C27548731", "wikidata": "https://www.wikidata.org/wiki/Q88272", "display_name": "Investment (military)", "level": 3, "score": 0.75857925}, {"id": "https://openalex.org/C31173074", "wikidata": "https://www.wikidata.org/wiki/Q2632514", "display_name": "Attractiveness", "level": 2, "score": 0.682596}, {"id": "https://openalex.org/C83646750", "wikidata": "https://www.wikidata.org/wiki/Q193893", "display_name": "Capital (architecture)", "level": 2, "score": 0.5948087}, {"id": "https://openalex.org/C2779343474", "wikidata": "https://www.wikidata.org/wiki/Q3109175", "display_name": "Context (archaeology)", "level": 2, "score": 0.5474126}, {"id": "https://openalex.org/C110121322", "wikidata": "https://www.wikidata.org/wiki/Q865811", "display_name": "Distribution (mathematics)", "level": 2, "score": 0.48802772}, {"id": "https://openalex.org/C144133560", "wikidata": "https://www.wikidata.org/wiki/Q4830453", "display_name": "Business", "level": 0, "score": 0.48449585}, {"id": "https://openalex.org/C2988954192", "wikidata": "https://www.wikidata.org/wiki/Q482379", "display_name": "Regional development", "level": 2, "score": 0.4239359}, {"id": "https://openalex.org/C2985722716", "wikidata": "https://www.wikidata.org/wiki/Q4290", "display_name": "Capital investment", "level": 2, "score": 0.4225284}, {"id": "https://openalex.org/C74363100", "wikidata": "https://www.wikidata.org/wiki/Q273005", "display_name": "Economic system", "level": 1, "score": 0.4224516}, {"id": "https://openalex.org/C148383697", "wikidata": "https://www.wikidata.org/wiki/Q1781695", "display_name": "Regional science", "level": 1, "score": 0.4086362}, {"id": "https://openalex.org/C26271046", "wikidata": "https://www.wikidata.org/wiki/Q187097", "display_name": "Economic geography", "level": 1, "score": 0.36203587}, {"id": "https://openalex.org/C162324750", "wikidata": "https://www.wikidata.org/wiki/Q8134", "display_name": "Economics", "level": 0, "score": 0.2917449}, {"id": "https://openalex.org/C205649164", "wikidata": "https://www.wikidata.org/wiki/Q1071", "display_name": "Geography", "level": 0, "score": 0.26466414}, {"id": "https://openalex.org/C17744445", "wikidata": "https://www.wikidata.org/wiki/Q36442", "display_name": "Political science", "level": 0, "score": 0.21012375}, {"id": "https://openalex.org/C10138342", "wikidata": "https://www.wikidata.org/wiki/Q43015", "display_name": "Finance", "level": 1, "score": 0.19092399}, {"id": "https://openalex.org/C15744967", "wikidata": "https://www.wikidata.org/wiki/Q9418", "display_name": "Psychology", "level": 0, "score": 0.0}, {"id": "https://openalex.org/C134306372", "wikidata": "https://www.wikidata.org/wiki/Q7754", "display_name": "Mathematical analysis", "level": 1, "score": 0.0}, {"id": "https://openalex.org/C33923547", "wikidata": "https://www.wikidata.org/wiki/Q395", "display_name": "Mathematics", "level": 0, "score": 0.0}, {"id": "https://openalex.org/C166957645", "wikidata": "https://www.wikidata.org/wiki/Q23498", "display_name": "Archaeology", "level": 1, "score": 0.0}, {"id": "https://openalex.org/C94625758", "wikidata": "https://www.wikidata.org/wiki/Q7163", "display_name": "Politics", "level": 2, "score": 0.0}, {"id": "https://openalex.org/C11171543", "wikidata": "https://www.wikidata.org/wiki/Q41630", "display_name": "Psychoanalysis", "level": 1, "score": 0.0}, {"id": "https://openalex.org/C199539241", "wikidata": "https://www.wikidata.org/wiki/Q7748", "display_name": "Law", "level": 1, "score": 0.0}], "mesh": [], "locations_count": 1, "locations": [{"is_oa": true, "landing_page_url": "https://doi.org/10.32782/2523-4803/73-3-2", "pdf_url": null, "source": {"id": "https://openalex.org/S4210181594", "display_name": "Scientific Notes of Taurida National V I Vernadsky University Series Economy and Management", "issn_l": "2523-4803", "issn": ["2523-4803", "2707-1103"], "is_oa": true, "is_in_doaj": false, "is_indexed_in_scopus": false, "is_core": false, "host_organization": null, "host_organization_name": null, "host_organization_lineage": [], "host_organization_lineage_names": [], "type": "journal"}, "license": null, "license_id": null, "version": "publishedVersion", "is_accepted": true, "is_published": true}], "best_oa_location": {"is_oa": true, "landing_page_url": "https://doi.org/10.32782/2523-4803/73-3-2", "pdf_url": null, "source": {"id": "https://openalex.org/S4210181594", "display_name": "Scientific Notes of Taurida National V I Vernadsky University Series Economy and Management", "issn_l": "2523-4803", "issn": ["2523-4803", "2707-1103"], "is_oa": true, "is_in_doaj": false, "is_indexed_in_scopus": false, "is_core": false, "host_organization": null, "host_organization_name": null, "host_organization_lineage": [], "host_organization_lineage_names": [], "type": "journal"}, "license": null, "license_id": null, "version": "publishedVersion", "is_accepted": true, "is_published": true}, "sustainable_development_goals": [{"score": 0.5, "display_name": "Partnerships for the goals", "id": "https://metadata.un.org/sdg/17"}], "grants": [], "datasets": [], "versions": [], "referenced_works_count": 3, "referenced_works": ["https://openalex.org/W2912101916", "https://openalex.org/W3036211160", "https://openalex.org/W3091168554"], "related_works": ["https://openalex.org/W4375829797", "https://openalex.org/W4245080958", "https://openalex.org/W4200508654", "https://openalex.org/W3160315211", "https://openalex.org/W2577455382", "https://openalex.org/W2398900508", "https://openalex.org/W2083612000", "https://openalex.org/W1983826204", "https://openalex.org/W1966920876", "https://openalex.org/W1597520312"], "abstract_inverted_index": {"The": [0, 24, 114, 303], "article": [1, 115], "examines": [2], "the": [3, 7, 11, 27, 31, 37, 42, 55, 58, 60, 67, 72, 98, 118, 130, 150, 161, 172, 175, 184, 192, 198, 206, 214, 219, 251, 257, 262, 299, 309, 319, 328], "peculiarities": [4], "of": [5, 10, 13, 18, 21, 26, 33, 39, 57, 62, 69, 89, 97, 112, 120, 125, 132, 137, 142, 149, 152, 157, 174, 180, 186, 194, 197, 200, 209, 213, 216, 226, 238, 242, 247, 253, 259, 275, 282, 290, 294], "ensuring": [6], "investment": [8, 90, 188, 195, 211, 227, 254, 271, 277], "development": [9, 212, 225, 235, 246, 252, 274, 284, 289], "regions": [12, 68, 96, 124, 199, 215], "Ukraine,": [14], "characterizes": [15], "a": [16, 49, 109, 178], "complex": [17, 179], "problematic": [19], "aspects": [20], "this": [22], "topic.": [23], "materials": [25, 173], "scientific": [28, 176, 316], "research": [29, 305, 310], "analyzed": [30, 168], "amount": [32], "capital": [34, 91, 121, 133, 153, 189], "investments": [35, 122, 134, 154, 295], "in": [36, 41, 94, 127, 144, 160, 164, 183, 204, 218, 269, 308], "economy": [38], "Ukraine": [40, 70, 126, 143, 201, 217], "period": [43, 74, 111], "from": [44, 75, 298], "2010": [45, 76], "to": [46, 77, 84], "2020": [47, 78], "as": [48, 325, 327], "whole": [50], "and": [51, 169, 190, 229, 261, 280, 296, 314, 323], "by": [52, 123, 135, 140, 155, 236], "region.": [53], "In": [54, 171], "context": [56], "research,": [59, 177], "existence": [61], "significant": [63], "territorial": [64], "differentiations": [65], "between": [66, 92], "during": [71], "specified": [73], "was": [79], "revealed.": [80], "This": [81], "problem": [82], "leads": [83], "an": [85], "erroneous,": [86], "insufficient": [87], "distribution": [88], "projects": [93], "different": [95], "state,": [99], "and,": [100], "therefore,": [101], "makes": [102], "their": [103, 230, 243], "implementation": [104, 281], "difficult": [105], "or": [106], "impossible": [107], "over": [108], "certain": [110], "time.": [113], "separately": [116, 167], "analyzes": [117], "volume": [119, 131, 151], "2022,": [128], "determines": [129], "types": [136, 156], "economic": [138, 158, 313], "activity": [139, 159, 255], "region": [141, 163], "2022.": [145], "A": [146], "dot": [147], "diagram": [148], "Dnipropetrovsk": [162], "2022": [165], "is": [166, 202], "illustrated.": [170], "appropriate": [181], "measures": [182], "direction": [185], "attracting": [187], "increasing": [191], "level": [193], "attractiveness": [196], "defined": [203], "detail,": [205], "key": [207], "problems": [208], "effective": [210], "long": [220], "term": [221], "are": [222], "identified,": [223], "namely:": [224], "passports": [228], "placement": [231], "on": [232], "community": [233], "websites;": [234], "communities": [237], "spatial": [239], "planning": [240], "schemes": [241], "own": [244], "territory;": [245], "regional": [248, 276, 283], "programs": [249], "for": [250], "with": [256, 265], "involvement": [258], "business": [260], "public;": [263], "cooperation": [264], "international": [266], "organizations": [267], "involved": [268], "supporting": [270], "attraction": [272], "processes;": [273], "programs,": [278], "formation": [279], "budgets;": [285], "state": [286, 300], "infrastructure": [287], "support:": [288], "logistics": [291], "infrastructure,": [292], "financing": [293], "innovations": [297], "budget,": [301], "etc.": [302], "main": [304], "methods": [306], "used": [307], "were": [311], "general": [312], "special": [315], "methods,": [317], "including": [318], "abstract": [320], "method,": [321], "analysis": [322], "synthesis,": [324], "well": [326], "statistical": [329], "method.": [330]}, "abstract_inverted_index_v3": null, "cited_by_api_url": "https://api.openalex.org/works?filter=cites:W4389938214", "counts_by_year": [], "updated_date": "2025-06-18T08:35:27.630719", "created_date": "2023-12-20"}