{"id": "https://openalex.org/W4386660185", "doi": "https://doi.org/10.1088/1742-6596/2021/1/012011", "title": "Research on Conductive Polymer Materials", "display_name": "Research on Conductive Polymer Materials", "publication_year": 2021, "publication_date": "2021-10-01", "ids": {"openalex": "https://openalex.org/W4386660185", "doi": "https://doi.org/10.1088/1742-6596/2021/1/012011"}, "language": "en", "primary_location": {"is_oa": true, "landing_page_url": "https://doi.org/10.1088/1742-6596/2021/1/012011", "pdf_url": "https://iopscience.iop.org/article/10.1088/1742-6596/2021/1/012011/pdf", "source": {"id": "https://openalex.org/S4210187594", "display_name": "Journal of Physics Conference Series", "issn_l": "1742-6588", "issn": ["1742-6588", "1742-6596"], "is_oa": true, "is_in_doaj": false, "is_indexed_in_scopus": false, "is_core": true, "host_organization": "https://openalex.org/P4310320083", "host_organization_name": "IOP Publishing", "host_organization_lineage": ["https://openalex.org/P4310311669", "https://openalex.org/P4310320083"], "host_organization_lineage_names": ["Institute of Physics", "IOP Publishing"], "type": "journal"}, "license": null, "license_id": null, "version": "publishedVersion", "is_accepted": true, "is_published": true}, "type": "article", "type_crossref": "journal-article", "indexed_in": ["crossref"], "open_access": {"is_oa": true, "oa_status": "gold", "oa_url": "https://iopscience.iop.org/article/10.1088/1742-6596/2021/1/012011/pdf", "any_repository_has_fulltext": false}, "authorships": [{"author_position": "first", "author": {"id": "https://openalex.org/A5049986225", "display_name": "Jingxun Zhang", "orcid": null}, "institutions": [{"id": "https://openalex.org/I4210131125", "display_name": "Huanghuai University", "ror": "https://ror.org/02k92ks68", "country_code": "CN", "type": "funder", "lineage": ["https://openalex.org/I4210131125"]}], "countries": ["CN"], "is_corresponding": false, "raw_author_name": "Jingxun Zhang", "raw_affiliation_strings": ["Department of Chemistry and Chemical Engineering, Huanghuai University, Zhumadian 463000, China"], "affiliations": [{"raw_affiliation_string": "Department of Chemistry and Chemical Engineering, Huanghuai University, Zhumadian 463000, China", "institution_ids": ["https://openalex.org/I4210131125"]}]}, {"author_position": "middle", "author": {"id": "https://openalex.org/A5000408731", "display_name": "Wei Yu", "orcid": "https://orcid.org/0000-0002-8913-5985"}, "institutions": [{"id": "https://openalex.org/I4210131125", "display_name": "Huanghuai University", "ror": "https://ror.org/02k92ks68", "country_code": "CN", "type": "funder", "lineage": ["https://openalex.org/I4210131125"]}], "countries": ["CN"], "is_corresponding": false, "raw_author_name": "Yu Wei", "raw_affiliation_strings": ["Department of Chemistry and Chemical Engineering, Huanghuai University, Zhumadian 463000, China"], "affiliations": [{"raw_affiliation_string": "Department of Chemistry and Chemical Engineering, Huanghuai University, Zhumadian 463000, China", "institution_ids": ["https://openalex.org/I4210131125"]}]}, {"author_position": "middle", "author": {"id": "https://openalex.org/A5101964007", "display_name": "Jiatong Wang", "orcid": "https://orcid.org/0009-0005-4215-7262"}, "institutions": [{"id": "https://openalex.org/I4210131125", "display_name": "Huanghuai University", "ror": "https://ror.org/02k92ks68", "country_code": "CN", "type": "funder", "lineage": ["https://openalex.org/I4210131125"]}], "countries": ["CN"], "is_corresponding": false, "raw_author_name": "Jiatong Wang", "raw_affiliation_strings": ["Department of Chemistry and Chemical Engineering, Huanghuai University, Zhumadian 463000, China"], "affiliations": [{"raw_affiliation_string": "Department of Chemistry and Chemical Engineering, Huanghuai University, Zhumadian 463000, China", "institution_ids": ["https://openalex.org/I4210131125"]}]}, {"author_position": "middle", "author": {"id": "https://openalex.org/A5100705473", "display_name": "Mengyuan Liu", "orcid": "https://orcid.org/0000-0002-6415-9788"}, "institutions": [{"id": "https://openalex.org/I4210131125", "display_name": "Huanghuai University", "ror": "https://ror.org/02k92ks68", "country_code": "CN", "type": "funder", "lineage": ["https://openalex.org/I4210131125"]}], "countries": ["CN"], "is_corresponding": false, "raw_author_name": "Mengyuan Liu", "raw_affiliation_strings": ["Department of Chemistry and Chemical Engineering, Huanghuai University, Zhumadian 463000, China"], "affiliations": [{"raw_affiliation_string": "Department of Chemistry and Chemical Engineering, Huanghuai University, Zhumadian 463000, China", "institution_ids": ["https://openalex.org/I4210131125"]}]}, {"author_position": "last", "author": {"id": "https://openalex.org/A5102913812", "display_name": "Sun Lu", "orcid": "https://orcid.org/0009-0007-3276-6405"}, "institutions": [{"id": "https://openalex.org/I4210131125", "display_name": "Huanghuai University", "ror": "https://ror.org/02k92ks68", "country_code": "CN", "type": "funder", "lineage": ["https://openalex.org/I4210131125"]}], "countries": ["CN"], "is_corresponding": false, "raw_author_name": "Lu Sun", "raw_affiliation_strings": ["Department of Chemistry and Chemical Engineering, Huanghuai University, Zhumadian 463000, China"], "affiliations": [{"raw_affiliation_string": "Department of Chemistry and Chemical Engineering, Huanghuai University, Zhumadian 463000, China", "institution_ids": ["https://openalex.org/I4210131125"]}]}], "institution_assertions": [], "countries_distinct_count": 1, "institutions_distinct_count": 1, "corresponding_author_ids": [], "corresponding_institution_ids": [], "apc_list": null, "apc_paid": null, "fwci": 0.543, "has_fulltext": false, "cited_by_count": 2, "citation_normalized_percentile": {"value": 0.732576, "is_in_top_1_percent": false, "is_in_top_10_percent": false}, "cited_by_percentile_year": {"min": 66, "max": 71}, "biblio": {"volume": "2021", "issue": "1", "first_page": "012011", "last_page": "012011"}, "is_retracted": false, "is_paratext": false, "primary_topic": {"id": "https://openalex.org/T14155", "display_name": "Advanced Technology in Applications", "score": 0.3417, "subfield": {"id": "https://openalex.org/subfields/1710", "display_name": "Information Systems"}, "field": {"id": "https://openalex.org/fields/17", "display_name": "Computer Science"}, "domain": {"id": "https://openalex.org/domains/3", "display_name": "Physical Sciences"}}, "topics": [{"id": "https://openalex.org/T14155", "display_name": "Advanced Technology in Applications", "score": 0.3417, "subfield": {"id": "https://openalex.org/subfields/1710", "display_name": "Information Systems"}, "field": {"id": "https://openalex.org/fields/17", "display_name": "Computer Science"}, "domain": {"id": "https://openalex.org/domains/3", "display_name": "Physical Sciences"}}, {"id": "https://openalex.org/T14139", "display_name": "E-commerce and Technology Innovations", "score": 0.3294, "subfield": {"id": "https://openalex.org/subfields/1403", "display_name": "Business and International Management"}, "field": {"id": "https://openalex.org/fields/14", "display_name": "Business, Management and Accounting"}, "domain": {"id": "https://openalex.org/domains/2", "display_name": "Social Sciences"}}, {"id": "https://openalex.org/T12260", "display_name": "Educational Technology and Pedagogy", "score": 0.3181, "subfield": {"id": "https://openalex.org/subfields/1702", "display_name": "Artificial Intelligence"}, "field": {"id": "https://openalex.org/fields/17", "display_name": "Computer Science"}, "domain": {"id": "https://openalex.org/domains/3", "display_name": "Physical Sciences"}}], "keywords": [{"id": "https://openalex.org/keywords/investment", "display_name": "Investment", "score": 0.5101505}, {"id": "https://openalex.org/keywords/capital", "display_name": "Capital (architecture)", "score": 0.42762733}, {"id": "https://openalex.org/keywords/capital-investment", "display_name": "Capital investment", "score": 0.42135558}], "concepts": [{"id": "https://openalex.org/C27548731", "wikidata": "https://www.wikidata.org/wiki/Q88272", "display_name": "Investment (military)", "level": 3, "score": 0.5101505}, {"id": "https://openalex.org/C2778755073", "wikidata": "https://www.wikidata.org/wiki/Q10858537", "display_name": "Scale (ratio)", "level": 2, "score": 0.49539316}, {"id": "https://openalex.org/C98045186", "wikidata": "https://www.wikidata.org/wiki/Q205663", "display_name": "Process (computing)", "level": 2, "score": 0.48664674}, {"id": "https://openalex.org/C171250308", "wikidata": "https://www.wikidata.org/wiki/Q11468", "display_name": "Nanotechnology", "level": 1, "score": 0.4400467}, {"id": "https://openalex.org/C83646750", "wikidata": "https://www.wikidata.org/wiki/Q193893", "display_name": "Capital (architecture)", "level": 2, "score": 0.42762733}, {"id": "https://openalex.org/C110875604", "wikidata": "https://www.wikidata.org/wiki/Q75", "display_name": "The Internet", "level": 2, "score": 0.4275069}, {"id": "https://openalex.org/C2985722716", "wikidata": "https://www.wikidata.org/wiki/Q4290", "display_name": "Capital investment", "level": 2, "score": 0.42135558}, {"id": "https://openalex.org/C55587333", "wikidata": "https://www.wikidata.org/wiki/Q1133029", "display_name": "Engineering ethics", "level": 1, "score": 0.35906518}, {"id": "https://openalex.org/C144133560", "wikidata": "https://www.wikidata.org/wiki/Q4830453", "display_name": "Business", "level": 0, "score": 0.3530395}, {"id": "https://openalex.org/C192562407", "wikidata": "https://www.wikidata.org/wiki/Q228736", "display_name": "Materials science", "level": 0, "score": 0.2841215}, {"id": "https://openalex.org/C127413603", "wikidata": "https://www.wikidata.org/wiki/Q11023", "display_name": "Engineering", "level": 0, "score": 0.26800233}, {"id": "https://openalex.org/C41008148", "wikidata": "https://www.wikidata.org/wiki/Q21198", "display_name": "Computer science", "level": 0, "score": 0.2364212}, {"id": "https://openalex.org/C17744445", "wikidata": "https://www.wikidata.org/wiki/Q36442", "display_name": "Political science", "level": 0, "score": 0.16254342}, {"id": "https://openalex.org/C136764020", "wikidata": "https://www.wikidata.org/wiki/Q466", "display_name": "World Wide Web", "level": 1, "score": 0.088068545}, {"id": "https://openalex.org/C95457728", "wikidata": "https://www.wikidata.org/wiki/Q309", "display_name": "History", "level": 0, "score": 0.07886934}, {"id": "https://openalex.org/C121332964", "wikidata": "https://www.wikidata.org/wiki/Q413", "display_name": "Physics", "level": 0, "score": 0.0}, {"id": "https://openalex.org/C166957645", "wikidata": "https://www.wikidata.org/wiki/Q23498", "display_name": "Archaeology", "level": 1, "score": 0.0}, {"id": "https://openalex.org/C10138342", "wikidata": "https://www.wikidata.org/wiki/Q43015", "display_name": "Finance", "level": 1, "score": 0.0}, {"id": "https://openalex.org/C94625758", "wikidata": "https://www.wikidata.org/wiki/Q7163", "display_name": "Politics", "level": 2, "score": 0.0}, {"id": "https://openalex.org/C199539241", "wikidata": "https://www.wikidata.org/wiki/Q7748", "display_name": "Law", "level": 1, "score": 0.0}, {"id": "https://openalex.org/C111919701", "wikidata": "https://www.wikidata.org/wiki/Q9135", "display_name": "Operating system", "level": 1, "score": 0.0}, {"id": "https://openalex.org/C62520636", "wikidata": "https://www.wikidata.org/wiki/Q944", "display_name": "Quantum mechanics", "level": 1, "score": 0.0}], "mesh": [], "locations_count": 1, "locations": [{"is_oa": true, "landing_page_url": "https://doi.org/10.1088/1742-6596/2021/1/012011", "pdf_url": "https://iopscience.iop.org/article/10.1088/1742-6596/2021/1/012011/pdf", "source": {"id": "https://openalex.org/S4210187594", "display_name": "Journal of Physics Conference Series", "issn_l": "1742-6588", "issn": ["1742-6588", "1742-6596"], "is_oa": true, "is_in_doaj": false, "is_indexed_in_scopus": false, "is_core": true, "host_organization": "https://openalex.org/P4310320083", "host_organization_name": "IOP Publishing", "host_organization_lineage": ["https://openalex.org/P4310311669", "https://openalex.org/P4310320083"], "host_organization_lineage_names": ["Institute of Physics", "IOP Publishing"], "type": "journal"}, "license": null, "license_id": null, "version": "publishedVersion", "is_accepted": true, "is_published": true}], "best_oa_location": {"is_oa": true, "landing_page_url": "https://doi.org/10.1088/1742-6596/2021/1/012011", "pdf_url": "https://iopscience.iop.org/article/10.1088/1742-6596/2021/1/012011/pdf", "source": {"id": "https://openalex.org/S4210187594", "display_name": "Journal of Physics Conference Series", "issn_l": "1742-6588", "issn": ["1742-6588", "1742-6596"], "is_oa": true, "is_in_doaj": false, "is_indexed_in_scopus": false, "is_core": true, "host_organization": "https://openalex.org/P4310320083", "host_organization_name": "IOP Publishing", "host_organization_lineage": ["https://openalex.org/P4310311669", "https://openalex.org/P4310320083"], "host_organization_lineage_names": ["Institute of Physics", "IOP Publishing"], "type": "journal"}, "license": null, "license_id": null, "version": "publishedVersion", "is_accepted": true, "is_published": true}, "sustainable_development_goals": [{"id": "https://metadata.un.org/sdg/9", "display_name": "Industry, innovation and infrastructure", "score": 0.59}], "grants": [], "datasets": [], "versions": [], "referenced_works_count": 0, "referenced_works": [], "related_works": ["https://openalex.org/W4292064814", "https://openalex.org/W4233213501", "https://openalex.org/W2369981844", "https://openalex.org/W2360863633", "https://openalex.org/W2347835431", "https://openalex.org/W2083612000", "https://openalex.org/W2065457896", "https://openalex.org/W1983826204", "https://openalex.org/W1597520312", "https://openalex.org/W1595518739"], "abstract_inverted_index": {"With": [0], "the": [1, 5, 16, 19, 29, 32, 41, 51, 56, 59, 67, 78, 100, 116, 123], "continuous": [2], "improvement": [3], "of": [4, 18, 31, 58, 71, 80, 110, 118, 136], "national": [6], "science": [7], "and": [8, 34, 69, 73, 92, 94, 97, 133], "technology": [9, 47], "level,": [10], "some": [11, 144], "advanced": [12], "high-tech": [13], "has": [14, 22], "been": [15], "focus": [17], "country.": [20], "It": [21, 84, 140], "played": [23], "an": [24], "important": [25], "role": [26], "in": [27], "enhancing": [28], "lives": [30], "people": [33], "improving": [35], "their": [36], "living": [37], "habits.": [38], "In": [39], "particular,": [40], "technical": [42], "means": [43], "represented": [44], "by": [45], "Internet": [46], "have": [48], "completely": [49], "subverted": [50], "past": [52], "lifestyle.": [53], "But": [54], "for": [55], "development": [57, 70, 102], "entire": [60, 101], "country,": [61], "it": [62], "is": [63, 85, 104], "necessary": [64, 86], "to": [65, 87, 106, 129, 142], "strengthen": [66, 89], "research": [68, 79, 96, 117], "industry": [72], "new": [74, 111], "material": [75], "science,": [76], "especially": [77], "conductive": [81, 119, 138], "polymer": [82, 120, 137], "materials.": [83, 112, 139], "further": [88], "capital": [90], "investment": [91], "scientific": [93], "technological": [95], "ensure": [98], "that": [99], "process": [103], "able": [105], "obtain": [107], "large-scale": [108], "applications": [109], "This": [113], "article": [114], "takes": [115], "materials": [121], "as": [122], "topic": [124], "through": [125], "a": [126], "comprehensive": [127], "introduction": [128], "its": [130], "concept,": [131], "significance": [132], "effective": [134], "application": [135], "aims": [141], "bring": [143], "references.": [145]}, "abstract_inverted_index_v3": null, "cited_by_api_url": "https://api.openalex.org/works?filter=cites:W4386660185", "counts_by_year": [{"year": 2024, "cited_by_count": 1}, {"year": 2023, "cited_by_count": 1}], "updated_date": "2025-06-19T21:29:39.882001", "created_date": "2023-09-13"}