{"id": "https://openalex.org/W4405062216", "doi": "https://doi.org/10.47738/jads.v5i4.428", "title": "Utilizing Structural Equation Modelling to Evaluate Factors Affecting Investment Capital Attraction and Sustainable Development in Vietnam", "display_name": "Utilizing Structural Equation Modelling to Evaluate Factors Affecting Investment Capital Attraction and Sustainable Development in Vietnam", "publication_year": 2024, "publication_date": "2024-12-01", "ids": {"openalex": "https://openalex.org/W4405062216", "doi": "https://doi.org/10.47738/jads.v5i4.428"}, "language": "en", "primary_location": {"is_oa": true, "landing_page_url": "https://doi.org/10.47738/jads.v5i4.428", "pdf_url": null, "source": {"id": "https://openalex.org/S4210208405", "display_name": "Journal of Applied Data Sciences", "issn_l": "2723-6471", "issn": ["2723-6471"], "is_oa": true, "is_in_doaj": false, "is_indexed_in_scopus": true, "is_core": false, "host_organization": null, "host_organization_name": null, "host_organization_lineage": [], "host_organization_lineage_names": [], "type": "journal"}, "license": null, "license_id": null, "version": "publishedVersion", "is_accepted": true, "is_published": true}, "type": "article", "type_crossref": "journal-article", "indexed_in": ["crossref"], "open_access": {"is_oa": true, "oa_status": "gold", "oa_url": "https://doi.org/10.47738/jads.v5i4.428", "any_repository_has_fulltext": false}, "authorships": [{"author_position": "first", "author": {"id": "https://openalex.org/A5041048246", "display_name": "Do Thi Lan Dai", "orcid": null}, "institutions": [{"id": "https://openalex.org/I4210134642", "display_name": "Lac Hong University", "ror": "https://ror.org/03nypmk85", "country_code": "VN", "type": "funder", "lineage": ["https://openalex.org/I4210134642"]}], "countries": ["VN"], "is_corresponding": true, "raw_author_name": "Do Thi Lan Dai", "raw_affiliation_strings": ["Board of Lac Hong University (LHU), Bien Hoa City, Dong Nai Province, Vietnam"], "affiliations": [{"raw_affiliation_string": "Board of Lac Hong University (LHU), Bien Hoa City, Dong Nai Province, Vietnam", "institution_ids": ["https://openalex.org/I4210134642"]}]}], "institution_assertions": [], "countries_distinct_count": 1, "institutions_distinct_count": 1, "corresponding_author_ids": ["https://openalex.org/A5041048246"], "corresponding_institution_ids": ["https://openalex.org/I4210134642"], "apc_list": null, "apc_paid": null, "fwci": 0.0, "has_fulltext": false, "cited_by_count": 0, "citation_normalized_percentile": {"value": 0.0, "is_in_top_1_percent": false, "is_in_top_10_percent": false}, "cited_by_percentile_year": {"min": 0, "max": 74}, "biblio": {"volume": "5", "issue": "4", "first_page": "1678", "last_page": "1691"}, "is_retracted": false, "is_paratext": false, "primary_topic": {"id": "https://openalex.org/T10438", "display_name": "Energy, Environment, Economic Growth", "score": 0.5617, "subfield": {"id": "https://openalex.org/subfields/2002", "display_name": "Economics and Econometrics"}, "field": {"id": "https://openalex.org/fields/20", "display_name": "Economics, Econometrics and Finance"}, "domain": {"id": "https://openalex.org/domains/2", "display_name": "Social Sciences"}}, "topics": [{"id": "https://openalex.org/T10438", "display_name": "Energy, Environment, Economic Growth", "score": 0.5617, "subfield": {"id": "https://openalex.org/subfields/2002", "display_name": "Economics and Econometrics"}, "field": {"id": "https://openalex.org/fields/20", "display_name": "Economics, Econometrics and Finance"}, "domain": {"id": "https://openalex.org/domains/2", "display_name": "Social Sciences"}}], "keywords": [{"id": "https://openalex.org/keywords/capital", "display_name": "Capital (architecture)", "score": 0.5359007}, {"id": "https://openalex.org/keywords/investment", "display_name": "Investment", "score": 0.5260848}, {"id": "https://openalex.org/keywords/capital-investment", "display_name": "Capital investment", "score": 0.50428593}], "concepts": [{"id": "https://openalex.org/C71104824", "wikidata": "https://www.wikidata.org/wiki/Q1476639", "display_name": "Structural equation modeling", "level": 2, "score": 0.7706833}, {"id": "https://openalex.org/C2778364177", "wikidata": "https://www.wikidata.org/wiki/Q2247133", "display_name": "Attraction", "level": 2, "score": 0.73122185}, {"id": "https://openalex.org/C83646750", "wikidata": "https://www.wikidata.org/wiki/Q193893", "display_name": "Capital (architecture)", "level": 2, "score": 0.5359007}, {"id": "https://openalex.org/C27548731", "wikidata": "https://www.wikidata.org/wiki/Q88272", "display_name": "Investment (military)", "level": 3, "score": 0.5260848}, {"id": "https://openalex.org/C2985722716", "wikidata": "https://www.wikidata.org/wiki/Q4290", "display_name": "Capital investment", "level": 2, "score": 0.50428593}, {"id": "https://openalex.org/C552854447", "wikidata": "https://www.wikidata.org/wiki/Q131201", "display_name": "Sustainable development", "level": 2, "score": 0.49555266}, {"id": "https://openalex.org/C144133560", "wikidata": "https://www.wikidata.org/wiki/Q4830453", "display_name": "Business", "level": 0, "score": 0.38288006}, {"id": "https://openalex.org/C162324750", "wikidata": "https://www.wikidata.org/wiki/Q8134", "display_name": "Economics", "level": 0, "score": 0.37266818}, {"id": "https://openalex.org/C17744445", "wikidata": "https://www.wikidata.org/wiki/Q36442", "display_name": "Political science", "level": 0, "score": 0.17308322}, {"id": "https://openalex.org/C205649164", "wikidata": "https://www.wikidata.org/wiki/Q1071", "display_name": "Geography", "level": 0, "score": 0.15725878}, {"id": "https://openalex.org/C33923547", "wikidata": "https://www.wikidata.org/wiki/Q395", "display_name": "Mathematics", "level": 0, "score": 0.14823928}, {"id": "https://openalex.org/C10138342", "wikidata": "https://www.wikidata.org/wiki/Q43015", "display_name": "Finance", "level": 1, "score": 0.10587132}, {"id": "https://openalex.org/C105795698", "wikidata": "https://www.wikidata.org/wiki/Q12483", "display_name": "Statistics", "level": 1, "score": 0.08296102}, {"id": "https://openalex.org/C138885662", "wikidata": "https://www.wikidata.org/wiki/Q5891", "display_name": "Philosophy", "level": 0, "score": 0.0}, {"id": "https://openalex.org/C41895202", "wikidata": "https://www.wikidata.org/wiki/Q8162", "display_name": "Linguistics", "level": 1, "score": 0.0}, {"id": "https://openalex.org/C166957645", "wikidata": "https://www.wikidata.org/wiki/Q23498", "display_name": "Archaeology", "level": 1, "score": 0.0}, {"id": "https://openalex.org/C94625758", "wikidata": "https://www.wikidata.org/wiki/Q7163", "display_name": "Politics", "level": 2, "score": 0.0}, {"id": "https://openalex.org/C199539241", "wikidata": "https://www.wikidata.org/wiki/Q7748", "display_name": "Law", "level": 1, "score": 0.0}], "mesh": [], "locations_count": 1, "locations": [{"is_oa": true, "landing_page_url": "https://doi.org/10.47738/jads.v5i4.428", "pdf_url": null, "source": {"id": "https://openalex.org/S4210208405", "display_name": "Journal of Applied Data Sciences", "issn_l": "2723-6471", "issn": ["2723-6471"], "is_oa": true, "is_in_doaj": false, "is_indexed_in_scopus": true, "is_core": false, "host_organization": null, "host_organization_name": null, "host_organization_lineage": [], "host_organization_lineage_names": [], "type": "journal"}, "license": null, "license_id": null, "version": "publishedVersion", "is_accepted": true, "is_published": true}], "best_oa_location": {"is_oa": true, "landing_page_url": "https://doi.org/10.47738/jads.v5i4.428", "pdf_url": null, "source": {"id": "https://openalex.org/S4210208405", "display_name": "Journal of Applied Data Sciences", "issn_l": "2723-6471", "issn": ["2723-6471"], "is_oa": true, "is_in_doaj": false, "is_indexed_in_scopus": true, "is_core": false, "host_organization": null, "host_organization_name": null, "host_organization_lineage": [], "host_organization_lineage_names": [], "type": "journal"}, "license": null, "license_id": null, "version": "publishedVersion", "is_accepted": true, "is_published": true}, "sustainable_development_goals": [], "grants": [], "datasets": [], "versions": [], "referenced_works_count": 0, "referenced_works": [], "related_works": ["https://openalex.org/W4386786398", "https://openalex.org/W4319783074", "https://openalex.org/W4282832460", "https://openalex.org/W4255464147", "https://openalex.org/W2138293586", "https://openalex.org/W2083612000", "https://openalex.org/W2080052720", "https://openalex.org/W1983826204", "https://openalex.org/W1597520312", "https://openalex.org/W1503179180"], "abstract_inverted_index": {"Vietnam": [0], "and": [1, 18, 30, 37, 47, 58, 78, 98, 131, 138, 159, 175, 190, 201, 216, 229, 238, 262], "several": [2], "nations": [3], "globally": [4], "are": [5], "facing": [6], "unparalleled": [7], "effects": [8], "of": [9, 15, 35, 44, 65, 110, 149, 156, 162, 205, 247, 256], "climate": [10], "change,": [11], "the": [12, 19, 33, 41, 48, 63, 71, 108, 116, 136, 147, 160, 254, 259], "progressive": [13], "exhaustion": [14], "natural": [16], "resources,": [17], "global": [20], "Covid-19": [21], "pandemic": [22], "alongside": [23], "non-traditional": [24], "security": [25], "threats.": [26], "These": [27], "tremendous": [28], "challenges": [29], "occurrences": [31], "underscore": [32], "significance": [34, 154, 174], "harmonious": [36], "balanced": [38], "development": [39, 51, 167, 184, 196, 211, 252], "among": [40], "three": [42, 128, 222], "pillars": [43], "economics,": [45], "society,": [46, 231], "environment.": [49], "Sustainable": [50], "has": [52], "emerged": [53], "as": [54], "an": [55, 59], "imperative": [56], "necessity": [57], "unavoidable": [60], "trajectory": [61], "in": [62, 168, 185, 197], "evolution": [64], "human": [66], "society.": [67], "This": [68, 170], "study": [69, 89, 207], "examines": [70], "principal": [72], "aspects": [73], "influencing": [74, 146], "investment": [75, 150, 163], "capital": [76, 164], "attraction": [77, 148, 161], "sustainable": [79, 166, 183, 195, 210, 224, 251], "development,": [80], "consequently": [81], "offering": [82], "suggestions": [83], "to": [84, 106, 113, 134, 193], "enhance": [85], "this": [86, 206], "process.": [87], "The": [88, 141, 203], "employed": [90], "two": [91], "methodologies:": [92], "qualitative": [93], "research,": [94], "executed": [95], "via": [96], "interviews,": [97], "concentrated": [99], "on": [100, 123, 182], "15": [101], "economic": [102, 225], "expert": [103], "group": [104], "talks": [105], "modify": [107], "substance": [109], "observable": [111], "factors": [112], "align": [114], "with": [115, 152], "business's": [117], "features.": [118], "Quantitative": [119], "research": [120, 139], "was": [121], "conducted": [122], "800": [124], "representative": [125], "managers": [126], "from": [127], "Vietnamese": [129], "provinces": [130], "one": [132], "city": [133], "evaluate": [135], "model": [137], "assumptions.": [140], "results": [142], "indicate": [143], "five": [144, 157], "elements": [145], "capital,": [151], "a": [153, 177, 227, 235, 244], "level": [155], "percent,": [158], "impacting": [165], "Vietnam.": [169, 186], "contribution": [171], "enhances": [172], "academic": [173], "is": [176, 208], "reference": [178], "for": [179, 250], "future": [180], "studies": [181], "Five": [187], "policy": [188], "implications": [189], "contributions": [191], "exist": [192], "advancing": [194, 221], "Vietnam,": [198], "fostering": [199], "innovation": [200], "enthusiasm.": [202], "novelty": [204], "that": [209], "will": [212], "establish": [213], "Vietnam's": [214], "working": [215], "living": [217], "environment": [218], "by": [219], "concurrently": [220], "dimensions:": [223], "growth,": [226], "prosperous": [228], "equitable": [230], "stable": [232], "cultural": [233], "diversity,": [234], "pristine": [236], "environment,": [237], "preserved": [239], "resources": [240], "maintained": [241], "sustainably.": [242], "Consequently,": [243], "comprehensive": [245], "framework": [246], "ethical": [248], "principles": [249], "encompasses": [253], "concepts": [255], "sustainability": [257], "across": [258], "economic,": [260], "social,": [261], "environmental": [263], "dimensions.": [264]}, "abstract_inverted_index_v3": null, "cited_by_api_url": "https://api.openalex.org/works?filter=cites:W4405062216", "counts_by_year": [], "updated_date": "2025-06-15T00:39:29.075321", "created_date": "2024-12-06"}